plotmath/__init__.py
plotmath/plotmath.py
plotmath-0.3.13.dist-info/licenses/LICENSE
plotmath-0.3.13.dist-info/METADATA
plotmath-0.3.13.dist-info/WHEEL
plotmath-0.3.13.dist-info/top_level.txt
plotmath-0.3.13.dist-info/RECORD
