Metadata-Version: 2.4
Name: plotmath
Version: 0.3.13
Summary: Automatically generates textbook graphs for mathematical functions.
Home-page: https://github.com/reneaas/plotmath
Author: René Alexander Ask
Author-email: rene.ask@icloud.com
Classifier: Programming Language :: Python :: 3
Classifier: License :: OSI Approved :: MIT License
Classifier: Operating System :: OS Independent
Requires-Python: >=3.7
License-File: LICENSE
Requires-Dist: numpy
Requires-Dist: matplotlib
Dynamic: author
Dynamic: author-email
Dynamic: classifier
Dynamic: description
Dynamic: description-content-type
Dynamic: home-page
Dynamic: license-file
Dynamic: requires-dist
Dynamic: requires-python
Dynamic: summary
